LICENSE
MANIFEST.in
README.md
setup.py
./src/mrworkserver/internals/dec.c
./src/mrworkserver/internals/module.c
./src/mrworkserver/internals/protocol.c
./src/mrworkserver/internals/unpack.c
./src/mrworkserver/internals/ws.c
src/mrworkserver/__init__.py
src/mrworkserver/lrudict.py
src/mrworkserver/mrqclient.py
src/mrworkserver/statserver.py
src/mrworkserver/workserver.py
src/mrworkserver.egg-info/PKG-INFO
src/mrworkserver.egg-info/SOURCES.txt
src/mrworkserver.egg-info/dependency_links.txt
src/mrworkserver.egg-info/requires.txt
src/mrworkserver.egg-info/top_level.txt
src/mrworkserver/html/stats.ten
src/mrworkserver/internals/dec.c
src/mrworkserver/internals/dec.h
src/mrworkserver/internals/module.c
src/mrworkserver/internals/module.h
src/mrworkserver/internals/protocol.c
src/mrworkserver/internals/protocol.h
src/mrworkserver/internals/py_defines.h
src/mrworkserver/internals/unpack.c
src/mrworkserver/internals/unpack.h
src/mrworkserver/internals/ws.c
src/mrworkserver/internals/ws.h