Metadata-Version: 2.1
Name: mrworkserver
Version: 0.11
Summary: A python work server written in C
Home-page: http://github.com/MarkReedZ/mrworkserver/
Author: Mark Reed
Author-email: markreed99@gmail.com
License: MIT
Keywords: web,asyncio
Platform: x86_64 Linux and MacOS X
Classifier: Development Status :: 2 - Pre-Alpha
Classifier: Intended Audience :: Developers
Classifier: Environment :: Web Environment
Classifier: License :: OSI Approved :: MIT License
Classifier: Operating System :: MacOS :: MacOS X
Classifier: Operating System :: POSIX :: Linux
Classifier: Programming Language :: C
Classifier: Programming Language :: Python :: 3.5
Classifier: Programming Language :: Python :: 3.6
Classifier: Programming Language :: Python :: Implementation :: CPython
Classifier: Topic :: Internet :: WWW/HTTP
License-File: LICENSE
